ztfidr/__init__.py
ztfidr/host.py
ztfidr/hostmass.py
ztfidr/io.py
ztfidr/lightcurve.py
ztfidr/linefitter.py
ztfidr/mw.py
ztfidr/plotting.py
ztfidr/salt2.py
ztfidr/sample.py
ztfidr/script.py
ztfidr/simulation.py
ztfidr/snid.py
ztfidr/spectroscopy.py
ztfidr/target.py
ztfidr/typing.py
ztfidr/utils.py
ztfidr-0.13.0.dist-info/LICENSE
ztfidr-0.13.0.dist-info/METADATA
ztfidr-0.13.0.dist-info/WHEEL
ztfidr-0.13.0.dist-info/top_level.txt
ztfidr-0.13.0.dist-info/RECORD
