Metadata-Version: 2.1
Name: ztfidr
Version: 0.13.0
Summary: Tools for ZTF Ia *Internal*DataReleases
Home-page: https://github.com/MickaelRigault/ztfdr
Author: Mickael Rigault
Author-email: m.rigault@ipnl.in2p3.fr
License-File: LICENSE
